LICENSE
MANIFEST.in
README.md
requirements.txt
setup.py
Ginit.egg-info/PKG-INFO
Ginit.egg-info/SOURCES.txt
Ginit.egg-info/dependency_links.txt
Ginit.egg-info/entry_points.txt
Ginit.egg-info/not-zip-safe
Ginit.egg-info/requires.txt
Ginit.egg-info/top_level.txt
ginit/__init__.py
ginit/__main__.py
ginit/module.py
ginit/util.py
ginit/visitor.py
ginit/generation/__init__.py
ginit/generation/init_generator.py
ginit/inspection/__init__.py
ginit/inspection/classes.py
ginit/inspection/constants.py
ginit/inspection/functions.py
ginit/inspection/imports.py
ginit/inspection/module.py
ginit/patching/__init__.py
ginit/patching/imports_patcher.py
tests/test_project/__init__.py
tests/test_project/test_async_functions.py
tests/test_project/test_classes.py
tests/test_project/test_constants.py
tests/test_project/test_functions.py
tests/test_project/test_submodule/__init__.py
tests/test_project/test_submodule/test_sub_functions.py
tests/test_project/test_submodule/test_submodule_3/__init__.py
tests/test_project/test_submodule/test_submodule_3/test_sub_classes.py
tests/test_project/test_submodule_2/__init__.py
tests/test_project/test_submodule_2/test_sub_functions_2.py