Metadata-Version: 1.2
Name: Ginit
Version: 1.0.0
Summary: Python __init__.py and __init__.pxd generator
Home-page: https://github.com/Drakkar-Software/ginit
Author: Drakkar-Software
Author-email: drakkar-software@protonmail.com
License: LGPL-3.0
Platform: UNKNOWN
Classifier: Development Status :: 4 - Beta
Classifier: Operating System :: OS Independent
Classifier: Operating System :: MacOS :: MacOS X
Classifier: Operating System :: Microsoft :: Windows
Classifier: Operating System :: POSIX
Classifier: Programming Language :: Python :: 3.7
Requires-Python: >=3.7
